setup.py
blockext/__init__.py
blockext/blocks.py
blockext/generate.py
blockext/helper.py
blockext/languages.py
blockext/server.py
blockext.egg-info/PKG-INFO
blockext.egg-info/SOURCES.txt
blockext.egg-info/dependency_links.txt
blockext.egg-info/requires.txt
blockext.egg-info/top_level.txt